README.md
setup.py
ndpy/__init__.py
ndpy.egg-info/PKG-INFO
ndpy.egg-info/SOURCES.txt
ndpy.egg-info/dependency_links.txt
ndpy.egg-info/top_level.txt