Metadata-Version: 2.1
Name: ndpy
Version: 0.0.0
Summary: N-dimensional sequences for Python
Home-page: https://github.com/billzorn/ndpy
Author: Bill Zorn
Author-email: bill.zorn@gmail.com
License: UNKNOWN
Platform: UNKNOWN
Classifier: Development Status :: 2 - Pre-Alpha
Classifier: Programming Language :: Python :: 3
Classifier: License :: OSI Approved :: MIT License
Classifier: Operating System :: OS Independent
Requires-Python: >=3.6
